pyresp/__init__.py
pyresp/pyresp.py
pyresp-1.0.4.dist-info/LICENSE
pyresp-1.0.4.dist-info/METADATA
pyresp-1.0.4.dist-info/WHEEL
pyresp-1.0.4.dist-info/top_level.txt
pyresp-1.0.4.dist-info/zip-safe
pyresp-1.0.4.dist-info/RECORD
