Metadata-Version: 2.1
Name: pyresp
Version: 1.0.4
Summary: fastapi的通用返回助手
Home-page: https://github.com/buyfakett
Author: buyfakett
Author-email: buyfakett@vip.qq.com
License: MIT
Requires-Python: >=3.6
License-File: LICENSE
Requires-Dist: pyyaml
